LICENSE
MANIFEST.in
README.md
setup.py
hbshare/VERSION.txt
hbshare/__init__.py
hbshare.egg-info/PKG-INFO
hbshare.egg-info/SOURCES.txt
hbshare.egg-info/dependency_links.txt
hbshare.egg-info/requires.txt
hbshare.egg-info/top_level.txt
hbshare/base/BaseIndex.py
hbshare/base/QueryException.py
hbshare/base/__init__.py
hbshare/base/data_api.py
hbshare/base/data_pro.py
hbshare/base/dateu.py
hbshare/base/formula.py
hbshare/base/upass.py
hbshare/base/vars.py
hbshare/db/ApiCfg.py
hbshare/db/ApiUtils.py
hbshare/db/__init__.py
hbshare/db/fund/__init__.py
hbshare/db/fund/cons.py
hbshare/db/fund/nav.py
hbshare/db/fund/product.py
hbshare/db/loader/__init__.py
hbshare/db/loader/data_query.py
hbshare/db/loader/data_save.py
hbshare/db/simu/__init__.py
hbshare/db/simu/cons.py
hbshare/db/simu/corp.py
hbshare/db/simu/fund_rolling_calculator.py
hbshare/db/simu/nav.py
hbshare/db/simu/simu_index.py
hbshare/db/simu/valuation.py
hbshare/fe/__init__.py
hbshare/fe/AAM/__init__.py
hbshare/fe/AAM/blmodel/__init__.py
hbshare/fe/AAM/blmodel/blmodel.py
hbshare/fe/AAM/blmodel/zep_test.py
hbshare/fe/CYP/__init__.py
hbshare/fe/CYP/buy_sell_data_analysis.py
hbshare/fe/CYP/cyp_functions.py
hbshare/fe/CYP/plot_function.py
hbshare/fe/CYP/quant_week_data.py
hbshare/fe/CYP/test_cyp.py
hbshare/fe/FOF/__init__.py
hbshare/fe/FOF/fof_analysis.py
hbshare/fe/Fund_classifier/__init__.py
hbshare/fe/Fund_classifier/classification.py
hbshare/fe/Machine_learning/__init__.py
hbshare/fe/Machine_learning/classifier.py
hbshare/fe/XZ/__init__.py
hbshare/fe/XZ/db_engine.py
hbshare/fe/XZ/functionality.py
hbshare/fe/XZ/on_time_job.py
hbshare/fe/XZ/project.py
hbshare/fe/XZ/config/__init__.py
hbshare/fe/XZ/config/config_pfa.py
hbshare/fe/asset_allocation/__init__.py
hbshare/fe/asset_allocation/black_litterman.py
hbshare/fe/asset_allocation/black_litterman_solver.py
hbshare/fe/asset_allocation/black_litterman_solver_test.py
hbshare/fe/asset_allocation/black_litterman_test.py
hbshare/fe/asset_allocation/data_loader.py
hbshare/fe/asset_allocation/data_loader_db.py
hbshare/fe/asset_allocation/efficient_frontier.py
hbshare/fe/asset_allocation/efficient_frontier_solver.py
