Metadata-Version: 1.2
Name: hbshare
Version: 3.7.92
Summary: Howbuy Quantitative Research SDK.Fund product data query and withdrawal tools provided by Howbuy fund company for investment research
Home-page: https://www.howbuy.com
Author: meng.lv
Author-email: 49007952@qq.com
Maintainer: meng.lv
Maintainer-email: 49007952@qq.com
License: BSD
Keywords: Global Financial Data
Platform: UNKNOWN
Classifier: Development Status :: 4 - Beta
Classifier: Programming Language :: Python :: 2.6
Classifier: Programming Language :: Python :: 2.7
Classifier: Programming Language :: Python :: 3.2
Classifier: Programming Language :: Python :: 3.3
Classifier: Programming Language :: Python :: 3.4
Classifier: Programming Language :: Python :: 3.5
Classifier: Programming Language :: Python :: 3.6
Classifier: Programming Language :: Python :: 3.7
Classifier: License :: OSI Approved :: BSD License
